experiments_csv/Experiment.py
experiments_csv/VERSION
experiments_csv/__init__.py
experiments_csv/dict_product.py
experiments_csv/dict_to_row.py
experiments_csv/plot_results.py
experiments_csv-0.5.5.dist-info/LICENSE
experiments_csv-0.5.5.dist-info/METADATA
experiments_csv-0.5.5.dist-info/WHEEL
experiments_csv-0.5.5.dist-info/top_level.txt
experiments_csv-0.5.5.dist-info/RECORD
