Metadata-Version: 2.1
Name: experiments_csv
Version: 0.5.5
Summary: Simple framework for running simulation experiments and recording them in a CSV file
Home-page: https://github.com/erelsgl/experiments_csv
Author: Erel Segal-Halevi
Author-email: erelsgl@gmail.com
License: MIT
Project-URL: Bug Reports, https://github.com/erelsgl/experiments_csv/issues
Project-URL: Source Code, https://github.com/erelsgl/experiments_csv
Keywords: experiments
Classifier: Development Status :: 2 - Pre-Alpha
Requires-Python: >=3.8
License-File: LICENSE
Requires-Dist: pandas >=2.2.2
Provides-Extra: plotting
Requires-Dist: matplotlib >=3.9.0 ; extra == 'plotting'
